tai_cli/__init__.py
tai_cli/azure/__init__.py
tai_cli/azure/psql.py
tai_cli/utils/loader.py
tai_cli/workflows/dbrestore.py
tai_cli-0.1.2.dist-info/METADATA
tai_cli-0.1.2.dist-info/WHEEL
tai_cli-0.1.2.dist-info/entry_points.txt
tai_cli-0.1.2.dist-info/RECORD
